smartmeter_austria_energy/__init__.py
smartmeter_austria_energy/constants.py
smartmeter_austria_energy/decrypt.py
smartmeter_austria_energy/exceptions.py
smartmeter_austria_energy/obis.py
smartmeter_austria_energy/obisdata.py
smartmeter_austria_energy/obisvalue.py
smartmeter_austria_energy/smartmeter.py
smartmeter_austria_energy/supplier.py
smartmeter_austria_energy-1.5.0.dist-info/licenses/LICENSE
smartmeter_austria_energy-1.5.0.dist-info/METADATA
smartmeter_austria_energy-1.5.0.dist-info/WHEEL
smartmeter_austria_energy-1.5.0.dist-info/top_level.txt
smartmeter_austria_energy-1.5.0.dist-info/RECORD
