Metadata-Version: 2.4
Name: smartmeter_austria_energy
Version: 1.5.0
Summary: Connect locally to a Kaifa smartmeter of an Austrian energy provider
Home-page: https://github.com/NECH2004/smartmeter_austria_energy
Author: @NECH2004
Project-URL: Bug Tracker, https://github.com/NECH2004/smartmeter_austria_energy/issues
Classifier: Programming Language :: Python :: 3.13
Classifier: License :: OSI Approved :: MIT License
Classifier: Operating System :: OS Independent
License-File: LICENSE
Dynamic: license-file
